assman/__init__.py
assman/__main__.py
assman/_version.py
assman-0.0.0.dist-info/METADATA
assman-0.0.0.dist-info/WHEEL
assman-0.0.0.dist-info/entry_points.txt
assman-0.0.0.dist-info/top_level.txt
assman-0.0.0.dist-info/RECORD
