Metadata-Version: 2.4
Name: assman
Version: 0.0.0
Summary: Work in progress.
Author-email: assman <assman@noreply.codeberg.org>
Project-URL: Homepage, https://codeberg.org/assman/assman
Project-URL: Bug Tracker, https://codeberg.org/assman/assman/issues
